mdsvg2png/cos_uploader.py
mdsvg2png/demo.md
mdsvg2png/demo.png
mdsvg2png/demo.svg
mdsvg2png/demo_output.md
mdsvg2png/mdsvg2png.py
mdsvg2png/svg2png.py
mdsvg2png-0.2.0.dist-info/METADATA
mdsvg2png-0.2.0.dist-info/WHEEL
mdsvg2png-0.2.0.dist-info/entry_points.txt
mdsvg2png-0.2.0.dist-info/licenses/LICENSE
mdsvg2png-0.2.0.dist-info/RECORD
