Metadata-Version: 2.4
Name: mdsvg2png
Version: 0.2.0
Summary: A tool to convert SVG images in Markdown files to PNG.
Project-URL: Homepage, https://github.com/honghe/mdsvg2png
Project-URL: Repository, https://github.com/honghe/mdsvg2png
Author: Honghe
License-File: LICENSE
Keywords: converter,markdown,png,svg
Classifier: Development Status :: 3 - Alpha
Classifier: Intended Audience :: Developers
Classifier: Programming Language :: Python :: 3
Classifier: Programming Language :: Python :: 3.10
Classifier: Programming Language :: Python :: 3.11
Classifier: Programming Language :: Python :: 3.12
Classifier: Programming Language :: Python :: 3.13
Classifier: Programming Language :: Python :: 3.14
Classifier: Topic :: Multimedia :: Video
Requires-Python: >=3.10
Requires-Dist: cos-python-sdk-v5
Requires-Dist: httpx
Requires-Dist: playwright
Requires-Dist: python-dotenv
Provides-Extra: dev
Requires-Dist: build; extra == 'dev'
Requires-Dist: twine; extra == 'dev'
